[
  { "src": "../Images/g1.jpg" },
  { "src": "../Images/g2.jpg" },
  { "src": "../Images/g3.jpg" },
  { "src": "../Images/g4.jpg" },
  { "src": "../Images/g5.jpg" },
  { "src": "../Images/g6.jpg" },
  { "src": "../Images/g7.png" },
  { "src": "../Images/g8.jpg" },
  { "src": "../Images/g9.jpg" },
  { "src": "../Images/g10.jpg" },
  { "src": "../Images/g11.jpg" },
  { "src": "../Images/g12.jpg" },
  { "src": "../Images/g13.jpg" },
  { "src": "../Images/g14.jpg" },
  { "src": "../Images/g15.jpg" },
  { "src": "../Images/g16.jpg" },
  { "src": "../Images/g17.jpg" },
  { "src": "../Images/g18.jpg" },
  { "src": "../Images/g19.jpg" },
  { "src": "../Images/g20.jpg" }
]
